configparserc.cpython-310-x86_64-linux-gnu.so
configparserc-3.0.2.dist-info/WHEEL
configparserc-3.0.2.dist-info/METADATA
configparserc-3.0.2.dist-info/top_level.txt
configparserc-3.0.2.dist-info/RECORD
configparserc-3.0.2.dist-info/LICENSE
