Metadata-Version: 2.1
Name: configparserc
Version: 3.0.2
Summary: Python (Cython) based implementation of ConfigParser based on POSIX and stdlib functions.
Author-email: Sergey Klyuykov <onegreyonewhite@mail.ru>
Maintainer-email: Sergey Klyuykov <onegreyonewhite@mail.ru>
License: Apache Software License
Project-URL: Issue Tracker, https://gitlab.com/onegreyonewhite/configparserc/issues
Project-URL: Source, https://gitlab.com/onegreyonewhite/configparserc
Keywords: config,configparser,configparserc,ini
Classifier: Development Status :: 5 - Production/Stable
Classifier: Operating System :: POSIX
Classifier: License :: OSI Approved :: Apache Software License
Classifier: Programming Language :: C
Classifier: Programming Language :: Cython
Classifier: Programming Language :: Python
Classifier: Programming Language :: Python :: 3
Classifier: Programming Language :: Python :: 3 :: Only
Classifier: Programming Language :: Python :: 3.10
Classifier: Programming Language :: Python :: 3.11
Classifier: Programming Language :: Python :: 3.12
Classifier: Programming Language :: Python :: 3.13
Classifier: Programming Language :: Python :: Implementation :: CPython
Classifier: Topic :: Software Development :: Libraries
Classifier: Topic :: Software Development :: Libraries :: Python Modules
Classifier: Topic :: Utilities
Requires-Python: >=3.10
License-File: LICENSE
Requires-Dist: pytimeparse2 ~=1.7.1
Requires-Dist: pyyaml <6.1,>=3.13
